dflipflop/dflipflop.v
module dff (
    input wire d, clk, rst,
    output reg q
);

always @(posedge clk or posedge rst) begin
    if (rst)
        q <= 1'b0;
    else
        q <= d;
end
    
endmodule

dflipflop/dflipflop_tb.v
`timescale 1ps/1ps

module dff_tb;
    reg d, clk, rst;
    wire q;

    dff d0(
        .d(d),
        .clk(clk),
        .rst(rst),
        .q(q)
    );

always #5 clk = ~clk;

initial begin
    $dumpfile("dff_tb.vcd");
    $dumpvars(0, dff_tb);

    clk = 0; rst = 1; #10;
    rst = 0; d = 1; #10;
    d = 0; #10;
    d = 1; #10;
    d = 0; #10
    #20;

    $finish;
end
endmodule

dflipflop/dff_tb.vcd
$date
	Fri Mar 07 19:12:26 2025
$end
$version
	Icarus Verilog
$end
$timescale
	1ps
$end
$scope module dff_tb $end
$var wire 1 ! q $end
$var reg 1 " clk $end
$var reg 1 # d $end
$var reg 1 $ rst $end
$scope module d0 $end
$var wire 1 % clk $end
$var wire 1 & d $end
$var wire 1 ' rst $end
$var reg 1 ( q $end
$upscope $end
$upscope $end
$enddefinitions $end
#0
$dumpvars
0(
1'
x&
0%
1$
x#
0"
0!
$end
#5
1"
1%
#10
0"
0%
1#
1&
0$
0'
#15
1(
1!
1"
1%
#20
0"
0%
0#
0&
#25
0(
0!
1"
1%
#30
0"
0%
1#
1&
#35
1(
1!
1"
1%
#40
0"
0%
0#
0&
#45
0(
0!
1"
1%
