Task4-6/alu.v
module alu (
    input wire [31:0] op1, op2,
    input wire [3:0] alu_control,
    output reg [31:0] result,
    output zero
);
parameter COMPLEMENT = 4'b0000;
parameter AND        = 4'b0001;
parameter XOR        = 4'b0010;
parameter OR         = 4'b0011;
parameter DECREMENT  = 4'b0100;
parameter ADD        = 4'b0101;
parameter SUB        = 4'b0110;
parameter INCREMENT  = 4'b0111;
always @(*) begin
    case(alu_control)
        COMPLEMENT: result = ~op1;
        AND       : result = op1 & op2;
        XOR       : result = op1 ^ op2;
        OR        : result = op1 | op2;
        DECREMENT : result = op1 - 32'd1;
        ADD       : result = op1 + op2;
        SUB       : result = op1 - op2;
        INCREMENT : result = op1 + 1;
        default: result = 0;
    endcase
end
assign zero = (result == 0);
endmodule

Task4-6/tb/alu_tb.v
`timescale 1ns / 1ps
`include "../alu.v"
module alu_tb;
    // Inputs
    reg [31:0] op1, op2;
    reg [3:0] alu_control;
    
    // Outputs
    wire [31:0] result;
    wire zero;
    
    // Instantiate the ALU module
    alu alu_inst (
        .op1(op1),
        .op2(op2),
        .alu_control(alu_control),
        .result(result),
        .zero(zero)
    );
    
    // Test procedure
    initial begin
        $dumpfile("../vcd/alu_tb.vcd");
        $dumpvars(0, alu_tb);
        // Initialize inputs
        op1 = 32'h00000000;
        op2 = 32'h00000000;
        alu_control = 4'b0000;
        
        // Test COMPLEMENT (~op1)
        #10;
        op1 = 32'hFFFFFFFF;
        alu_control = 4'b0000; // COMPLEMENT
        
        // Test AND (op1 & op2)
        #10;
        op1 = 32'hAAAA5555;
        op2 = 32'hFFFF0000;
        alu_control = 4'b0001; // AND       
        
        // Test XOR (op1 ^ op2)
        #10;
        op1 = 32'hAAAA5555;
        op2 = 32'hFFFF0000;
        alu_control = 4'b0010; // XOR
        
        // Test OR (op1 | op2)
        #10;
        op1 = 32'hAAAA5555;
        op2 = 32'hFFFF0000;
        alu_control = 4'b0011; // OR
        
        // Test DECREMENT (op1 - 1)
        #10;
        op1 = 32'h00000001;
        alu_control = 4'b0100; // DECREMENT
        
        // Test ADD (op1 + op2)
        #10;
        op1 = 32'h000000FF;
        op2 = 32'h00000001;
        alu_control = 4'b0101; // ADD
        
        // Test SUB (op1 - op2)
        #10;
        op1 = 32'h000000FF;
        op2 = 32'h00000001;
        alu_control = 4'b0110; // SUB
        
        // Test INCREMENT (op1 + 1)
        #10;
        op1 = 32'h000000FF;
        alu_control = 4'b0111; // INCREMENT
        
        // Test default case
        #10;
        op1 = 32'hAAAAAAAA;
        op2 = 32'h55555555;
        alu_control = 4'b1000; // Invalid control
        
        // Test zero flag
        #10;
        op1 = 32'h00000000;
        op2 = 32'h00000000;
        alu_control = 4'b0101; // ADD (result should be 0)
        
        // Finish simulation
        #10;
        $finish;
    end
endmodule

Task4-6/vcd/alu_tb.vcd
$date
    May 15, 2025  17:46:58
$end
$version
    TOOL:	xmsim(64)	23.03-s007
$end
$timescale
    1 ps
$end

$scope module alu_tb $end
$var reg      32 !    op1 [31:0] $end
$var reg      32 "    op2 [31:0] $end
$var reg       4 #    alu_control [3:0] $end
$var wire     32 $    result [31:0] $end
$var wire      1 %    zero  $end

$scope module alu_inst $end
$var wire     32 &    op1 [31:0] $end
$var wire     32 '    op2 [31:0] $end
$var wire      4 (    alu_control [3:0] $end
$var reg      32 )    result [31:0] $end
$var wire      1 %    zero  $end
$var parameter  4 *    COMPLEMENT $end
$var parameter  4 +    AND $end
$var parameter  4 ,    XOR $end
$var parameter  4 -    OR $end
$var parameter  4 .    DECREMENT $end
$var parameter  4 /    ADD $end
$var parameter  4 0    SUB $end
$var parameter  4 1    INCREMENT $end
$upscope $end

$upscope $end

$enddefinitions $end
$dumpvars
b111 1
b110 0
b101 /
b100 .
b11 -
b10 ,
b1 +
b0 *
b0 !
b0 "
b0 #
b11111111111111111111111111111111 $
0%
b0 &
b0 '
b0 (
b11111111111111111111111111111111 )
$end
#10000
b11111111111111111111111111111111 !
b11111111111111111111111111111111 &
b0 )
1%
b0 $
#20000
b10101010101010100101010101010101 !
b11111111111111110000000000000000 "
b1 #
b1 (
b11111111111111110000000000000000 '
b10101010101010100101010101010101 &
b10101010101010100000000000000000 )
0%
b10101010101010100000000000000000 $
#30000
b10 #
b10 (
b1010101010101010101010101010101 )
b1010101010101010101010101010101 $
#40000
b11 #
b11 (
b11111111111111110101010101010101 )
b11111111111111110101010101010101 $
#50000
b1 !
b100 #
b100 (
b1 &
b0 )
1%
b0 $
#60000
b11111111 !
b1 "
b101 #
b101 (
b1 '
b11111111 &
b100000000 )
0%
b100000000 $
#70000
b110 #
b110 (
b11111110 )
b11111110 $
#80000
b111 #
b111 (
b100000000 )
b100000000 $
#90000
b10101010101010101010101010101010 !
b1010101010101010101010101010101 "
b1000 #
b1000 (
b1010101010101010101010101010101 '
b10101010101010101010101010101010 &
b0 )
1%
b0 $
#100000
b0 !
b0 "
b101 #
b101 (
b0 '
b0 &
