Task4-6/datamem.v
module datamem(
    input wire datamem_clk, 
    input wire datamem_MemWrite, datamem_MemRead,
    input wire [31:0] datamem_address,
    input wire [31:0] datamem_Write,
    output reg [31:0] datamem_Read
);
reg [31:0] Mem [0:1023];
always @(posedge datamem_clk) begin
    if (datamem_MemWrite) begin
        Mem[datamem_address[31:2]] <= datamem_Write;
    end
    else begin
        Mem[datamem_address[31:2]] <= Mem[datamem_address[31:2]];
    end
end
always @(*) begin
    if (datamem_MemRead) begin
        datamem_Read = Mem[datamem_address[31:2]];
    end
    else begin
        datamem_Read = 32'b0;
    end
end
endmodule

Task4-6/alu.v
module alu (
    input wire [31:0] alu_op1, alu_op2,
    input wire [3:0] alu_control,
    output reg [31:0] alu_result,
    output alu_zero
);
parameter COMPLEMENT = 4'b0000;
parameter AND        = 4'b0001;
parameter XOR        = 4'b0010;
parameter OR         = 4'b0011;
parameter DECREMENT  = 4'b0100;
parameter ADD        = 4'b0101;
parameter SUB        = 4'b0110;
parameter INCREMENT  = 4'b0111;
always @(*) begin
    case(alu_control)
        COMPLEMENT: alu_result = ~alu_op1;
        AND       : alu_result = alu_op1 & alu_op2;
        XOR       : alu_result = alu_op1 ^ alu_op2;
        OR        : alu_result = alu_op1 | alu_op2;
        DECREMENT : alu_result = alu_op1 - 32'd1;
        ADD       : alu_result = alu_op1 + alu_op2;
        SUB       : alu_result = alu_op1 - alu_op2;
        INCREMENT : alu_result = alu_op1 + 1;
        default: alu_result = 0;
    endcase
end
assign alu_zero = (alu_result == 0);
endmodule

Task4-6/sign_extend.v
module sign_extend(
    input [15:0] signextend_in,
    output [31:0] signextend_out
);
assign signextend_out = {{16{signextend_in[15]}}, signextend_in};
endmodule

Task4-6/rtl/regfile.v
module regfile(
    input wire regfile_clk, regfile_rst,
    input wire regfile_RegWrite,
    input wire [4:0] regfile_ReadReg1, regfile_ReadReg2, regfile_WriteReg, 
    input wire [31:0] regfile_WriteData,
    output reg [31:0] regfile_ReadData1, regfile_ReadData2
);

reg [31:0] Regs [0:31];
initial begin
    Regs[0] = 32'b0;
end

always @(posedge regfile_clk) begin
    if (!regfile_rst) begin
        Regs[0] <= 32'b0;
    end
    else if (regfile_RegWrite) begin
        if (regfile_WriteReg != 5'b00000) begin
            Regs[regfile_WriteReg] <= regfile_WriteData;
        end
    end
end

always @(*) begin
    regfile_ReadData1 = (regfile_ReadReg1 == 5'b00000) ? 32'b0 : Regs[regfile_ReadReg1];
    regfile_ReadData2 = (regfile_ReadReg2 == 5'b00000) ? 32'b0 : Regs[regfile_ReadReg2];
end
endmodule

Task4-6/controlunit.v
module controlunit(
    input [5:0] controlunit_opcode,
    input [5:0] controlunit_funct,
    output reg controlunit_RegDst, controlunit_MemRead, controlunit_MemWrite, controlunit_MemToReg, controlunit_ALUSrc, controlunit_RegWrite,
    output reg [3:0] controlunit_alu_control
);

always @(*) begin
    controlunit_RegDst = 0;
    controlunit_ALUSrc = 0;
    controlunit_MemToReg = 0;
    controlunit_RegWrite = 1;
    controlunit_MemRead = 0;
    controlunit_MemWrite = 0;
    controlunit_alu_control = 4'b0000;

    case(controlunit_opcode) 
        6'b000001 : begin
            controlunit_RegDst = 1;
            controlunit_ALUSrc = 0;
            controlunit_MemToReg = 0;
            controlunit_RegWrite = 0;
            controlunit_MemRead = 0;
            controlunit_MemWrite = 0;
            case (controlunit_funct) 
                6'b100000 : controlunit_alu_control = 4'b0101;
                default   : controlunit_alu_control = 4'b0000;
            endcase
        end
        6'b000100 : begin
            controlunit_RegDst = 0;
            controlunit_ALUSrc = 1;
            controlunit_MemToReg = 1;
            controlunit_RegWrite = 1;
            controlunit_MemRead = 1;
            controlunit_MemWrite = 0;
            controlunit_alu_control =  4'b0101;
        end
        6'b000010 : begin
            controlunit_RegDst = 0;
            controlunit_ALUSrc = 1;
            controlunit_MemToReg = 0;
            controlunit_RegWrite = 0;
            controlunit_MemRead = 0;
            controlunit_MemWrite = 1;
            controlunit_alu_control =  4'b0101;
        end
        default: begin
            controlunit_RegDst = 'bx;
            controlunit_ALUSrc = 'bx;
            controlunit_MemToReg = 'bx;
            controlunit_RegWrite = 'bx;
            controlunit_MemRead = 'bx;
            controlunit_MemWrite = 'bx;
            controlunit_alu_control = 'bxxxx;
        end
    endcase
end
endmodule

Task4-6/inmem.v
module inmem(
    input wire [31:0] inmem_address,
    output wire [31:0] inmem_instruction
);

reg [31:0] inmems [0:1023];

initial begin
    $readmemh("testcase.txt", inmems);
    $display("Instruction memory is loading");
end

assign inmem_instruction = inmems[inmem_address[31:2]];

endmodule

Task4-6/rtl/pc.v
module pc (
   input wire        clk,    
   input wire        rst,
   output reg [31:0] pc_out 
);
    initial begin
        pc_out = 32'b0;
    end

   always @(posedge clk or negedge rst) begin
      if (!rst)
        begin
           pc_out <= 32'b0;
        end
      else
        begin
           pc_out <= pc_out + 32'd4;
        end
   end

endmodule

Task4-6/datapath.v
`include "alu.v"
`include "sign_extend.v"
`include "controlunit.v"
`include "datamem.v"
`include "inmem.v"
`include "pc.v"
`include "regfile.v"
module datapath (
    input wire clk, rst,
    output wire RegWrite, MemWrite, MemRead,
    output wire [31:0] pc,
    output wire [31:0] instruction,
    output wire [31:0] ReadData2,
    output wire [31:0] ALU_Result
);

//Program counter
wire [31:0] pc_tmp;
wire [31:0] instruction_tmp;

assign pc = pc_tmp;
assign instruction = instruction_tmp;

pc pc_d(
    .clk(clk),
    .rst(rst),
    .pc_out(pc_tmp)
);

//Instruction Memory
inmem imem(
    .inmem_address(pc_tmp),
    .inmem_instruction(instruction_tmp)
);

//Instruction for datapath and control unit
wire [5:0] opcode       = instruction_tmp[31:26];
wire [4:0] rs           = instruction_tmp[25:21];
wire [4:0] rt           = instruction_tmp[20:16];
wire [4:0] rd           = instruction_tmp[15:11];
wire [5:0] funct        = instruction_tmp[5:0];
wire [15:0] immediate   = instruction_tmp[15:0];

//Control unit
wire RegDst, ALUSrc, MemToReg;
wire[3:0] ALU_Control;

controlunit cu(
    .controlunit_opcode(opcode),
    .controlunit_funct(funct),
    .controlunit_RegDst(RegDst),
    .controlunit_MemToReg(MemToReg),
    .controlunit_RegWrite(RegWrite),
    .controlunit_MemRead(MemRead),
    .controlunit_MemWrite(MemWrite),
    .controlunit_ALUSrc(ALUSrc),
    .controlunit_alu_control(ALU_Control)
);

//Reg File
wire [31:0] ReadData1;
wire [31:0] WriteData;
wire [4:0] WriteReg;
//Mux RegDst
assign WriteReg = (RegDst) ? rd : rt;
regfile rf(
    .regfile_clk(clk),
    .regfile_rst(rst),
    .regfile_ReadReg1(rs),
    .regfile_ReadReg2(rt),
    .regfile_WriteReg(WriteReg),
    .regfile_WriteData(WriteData),
    .regfile_RegWrite(RegWrite),
    .regfile_ReadData1(ReadData1),
    .regfile_ReadData2(ReadData2)
);

//Sign extend
wire [31:0] sign_extend_imme;
sign_extend se(
    .signextend_in(immediate),
    .signextend_out(sign_extend_imme)
);

//mux ALUSrc
wire [31:0] alu_op2;
assign alu_op2 = (ALUSrc) ? sign_extend_imme : ReadData2;
//ALU
alu al(
    .alu_op1(ReadData1),
    .alu_op2(alu_op2),
    .alu_control(ALU_Control),
    .alu_result(ALU_Result),
    .alu_zero()
);

wire [31:0] ReadData_Mem;
datamem dm(
    .datamem_clk(clk),
    .datamem_address(ALU_Result),
    .datamem_Write(ReadData2),
    .datamem_Read(ReadData_Mem),
    .datamem_MemRead(MemRead),
    .datamem_MemWrite(MemWrite)
);

assign WriteData = (MemToReg) ? ReadData_Mem : ALU_Result;

endmodule

Task4-6/datapath_tb.v
`timescale 1ns / 1ps
`include "./datapath.v"
module datapath_tb;

   // Clock and reset signals
   reg clk;
   reg rst;

   // Wires to connect to the datapath outputs
   wire RegWrite;
   wire MemWrite;
   wire MemRead;
   wire [31:0] pc;
   wire [31:0] instruction;
   wire [31:0] ReadData2;
   wire [31:0] ALU_Result;

   // Instantiate the datapath module
   datapath dut (
       .clk(clk),
       .rst(rst),
       .RegWrite(RegWrite),
       .MemWrite(MemWrite),
       .MemRead(MemRead),
       .pc(pc),
       .instruction(instruction),
       .ReadData2(ReadData2),
       .ALU_Result(ALU_Result)
   );

   // Clock generation
   always #5 clk = ~clk;

   // Test stimulus
   initial begin
        $dumpfile("./vcd/datapath.vcd");
        $dumpvars(0, datapath_tb);
       $display("Starting Testbench...");

       // Initialize inputs
       clk = 0;
       rst = 0; // Start with reset asserted (active-low)

       // Apply reset sequence
       #20; 
       rst = 1; // Release reset
       #10; // Wait one more cycle for PC to update to 0 and fetch first instruction

       // Display initial state
       $display("--- Initial State After Reset ---");
       $display("Time | PC       | Instruction | RegWrite | MemRead | MemWrite | ALU Result | Rd1 Addr | Rd2 Addr | Read Data1 | Read Data2 | Reg Write Data");
       $display("--------------------------------------------------------------------------------------------------------------------------------------------------------------------");
       $display("%4d | %8h | %11h | %8b | %7b | %8b | %10h | %8d | %8d | %10h | %10h | %14h",
                $time, pc, instruction, RegWrite, MemRead, MemWrite, ALU_Result,
                dut.rf.regfile_ReadReg1, dut.rf.regfile_ReadReg2, dut.rf.regfile_ReadData1, dut.rf.regfile_ReadData2, dut.rf.regfile_WriteData);

       // Initialize Data Memory
       $display("--- Initializing Data Memory ---");
       dut.dm.Mem[0] = 32'h00000100; // Mem[0x00]
       dut.dm.Mem[1] = 32'h00000200; // Mem[0x04]
       dut.dm.Mem[2] = 32'h00000300; // Mem[0x08]
       dut.dm.Mem[3] = 32'h00000400; // Mem[0x0C]
       dut.dm.Mem[4] = 32'h00000500; // Mem[0x10]
       dut.dm.Mem[5] = 32'h00000600; // Mem[0x14]
       dut.dm.Mem[6] = 32'h00000700; // Mem[0x18]
       dut.dm.Mem[7] = 32'h00000800; // Mem[0x1C]
       dut.dm.Mem[8] = 32'h00000900; // Mem[0x20]
       dut.dm.Mem[9] = 32'h00000A00; // Mem[0x24]
       dut.dm.Mem[64] = 32'hDEADBEEF; // Mem[0x100]
       dut.dm.Mem[65] = 32'hCAFEF00D; // Mem[0x104]
       dut.dm.Mem[66] = 32'hF0F0F0F0; // Mem[0x108]
       dut.dm.Mem[67] = 32'hDEADBEEF; // Mem[0x10C]
       dut.dm.Mem[68] = 32'hCAFEF00D; // Mem[0x110]
       dut.dm.Mem[69] = 32'hF0F0F0F0; // Mem[0x114]
       dut.dm.Mem[70] = 32'hDEADBEEF; // Mem[0x118]
       dut.dm.Mem[71] = 32'hCAFEF00D; // Mem[0x11C]
       dut.dm.Mem[72] = 32'hF0F0F0F0; // Mem[0x120]
       dut.dm.Mem[73] = 32'hDEADBEEF; // Mem[0x124]

       // Initialize Register File
       $display("--- Initializing Registers ---");
       dut.rf.Regs[8]  = 32'h00000000; // $t0 = 0
       dut.rf.Regs[9]  = 32'h0000000A; // $t1 = 10
       dut.rf.Regs[10] = 32'h00000014; // $t2 = 20
       dut.rf.Regs[11] = 32'h0000001E; // $t3 = 30
       dut.rf.Regs[12] = 32'h00000028; // $t4 = 40
       dut.rf.Regs[13] = 32'h00000032; // $t5 = 50
       dut.rf.Regs[14] = 32'h0000003C; // $t6 = 60
       dut.rf.Regs[15] = 32'h00000046; // $t7 = 70
       dut.rf.Regs[16] = 32'h00000050; // $s0 = 80
       dut.rf.Regs[17] = 32'h0000005A; // $s1 = 90
       dut.rf.Regs[18] = 32'h00000064; // $s2 = 100
       dut.rf.Regs[19] = 32'h0000006E; // $s3 = 110
       dut.rf.Regs[20] = 32'h00000078; // $s4 = 120
       dut.rf.Regs[21] = 32'h00000082; // $s5 = 130
       dut.rf.Regs[22] = 32'h0000008C; // $s6 = 140
       dut.rf.Regs[23] = 32'h00000096; // $s7 = 150
       dut.rf.Regs[0]  = 32'h00000000; // $zero = 0

       $display("--- Executing Instructions ---");
       // Execute 111 instructions
       repeat (111) begin
           @(posedge clk);
           $display("Time | PC       | Instruction | RegWrite | MemRead | MemWrite | ALU Result | Rd1 Addr | Rd2 Addr | Read Data1 | Read Data2 | Reg Write Data");
           $display("--------------------------------------------------------------------------------------------------------------------------------------------------------------------");
           $display("%4d | %8h | %11h | %8b | %7b | %8b | %10h | %8d | %8d | %10h | %10h | %14h",
                    $time, pc, instruction, RegWrite, MemRead, MemWrite, ALU_Result,
                    dut.rf.regfile_ReadReg1, dut.rf.regfile_ReadReg2, dut.rf.regfile_ReadData1, dut.rf.regfile_ReadData2, dut.rf.regfile_WriteData);
           // Display register file read data
           $display("       | Register File Read Data 1: %h, Read Data 2: %h",
                    dut.rf.regfile_ReadData1, dut.rf.regfile_ReadData2);
           // Display key register contents
           $display("       | $t0 (R8): %h, $t1 (R9): %h, $t2 (R10): %h, $t3 (R11): %h",
                    dut.rf.Regs[8], dut.rf.Regs[9], dut.rf.Regs[10], dut.rf.Regs[11]);
           $display("       | $t4 (R12): %h, $t5 (R13): %h, $t6 (R14): %h, $t7 (R15): %h",
                    dut.rf.Regs[12], dut.rf.Regs[13], dut.rf.Regs[14], dut.rf.Regs[15]);
           $display("       | $s0 (R16): %h, $s1 (R17): %h, $s2 (R18): %h, $s3 (R19): %h",
                    dut.rf.Regs[16], dut.rf.Regs[17], dut.rf.Regs[18], dut.rf.Regs[19]);
           $display("       | $s4 (R20): %h, $s5 (R21): %h, $s6 (R22): %h, $s7 (R23): %h",
                    dut.rf.Regs[20], dut.rf.Regs[21], dut.rf.Regs[22], dut.rf.Regs[23]);
           // Display key memory locations
           $display("       | Mem[Word 64 (0x100)]: %h, Mem[Word 65 (0x104)]: %h, Mem[Word 66 (0x108)]: %h",
                    dut.dm.Mem[64], dut.dm.Mem[65], dut.dm.Mem[66]);
           $display("       | Mem[Word 67 (0x10C)]: %h, Mem[Word 68 (0x110)]: %h, Mem[Word 69 (0x114)]: %h",
                    dut.dm.Mem[67], dut.dm.Mem[68], dut.dm.Mem[69]);
           $display("       | Mem[Word 70 (0x118)]: %h, Mem[Word 71 (0x11C)]: %h, Mem[Word 72 (0x120)]: %h, Mem[Word 73 (0x124)]: %h",
                    dut.dm.Mem[70], dut.dm.Mem[71], dut.dm.Mem[72], dut.dm.Mem[73]);
       end

       $display("--------------------------------------------------------------------------------------------------------------------------------------------------");
       $display("MIPS Datapath Testbench finished.");
       
       $finish; // End simulation
   end

endmodule

Task4-6/vcd/datapath.vcd
$date
	Sun May 18 19:21:53 2025
$end
$version
	Icarus Verilog
$end
$timescale
	1ps
$end
$scope module datapath_tb $end
$var wire 32 ! pc [31:0] $end
$var wire 32 " instruction [31:0] $end
$var wire 1 # RegWrite $end
$var wire 32 $ ReadData2 [31:0] $end
$var wire 1 % MemWrite $end
$var wire 1 & MemRead $end
$var wire 32 ' ALU_Result [31:0] $end
$var reg 1 ( clk $end
$var reg 1 ) rst $end
$scope module dut $end
$var wire 1 ( clk $end
$var wire 32 * instruction [31:0] $end
$var wire 32 + pc [31:0] $end
$var wire 1 ) rst $end
$var wire 32 , sign_extend_imme [31:0] $end
$var wire 5 - rt [4:0] $end
$var wire 5 . rs [4:0] $end
$var wire 5 / rd [4:0] $end
$var wire 32 0 pc_tmp [31:0] $end
$var wire 6 1 opcode [5:0] $end
$var wire 32 2 instruction_tmp [31:0] $end
$var wire 16 3 immediate [15:0] $end
$var wire 6 4 funct [5:0] $end
$var wire 32 5 alu_op2 [31:0] $end
$var wire 5 6 WriteReg [4:0] $end
$var wire 32 7 WriteData [31:0] $end
$var wire 1 # RegWrite $end
$var wire 1 8 RegDst $end
$var wire 32 9 ReadData_Mem [31:0] $end
$var wire 32 : ReadData2 [31:0] $end
$var wire 32 ; ReadData1 [31:0] $end
$var wire 1 % MemWrite $end
$var wire 1 < MemToReg $end
$var wire 1 & MemRead $end
$var wire 32 = ALU_Result [31:0] $end
$var wire 4 > ALU_Control [3:0] $end
$var wire 1 ? ALUSrc $end
$scope module al $end
$var wire 32 @ alu_op2 [31:0] $end
$var wire 1 A alu_zero $end
$var wire 32 B alu_op1 [31:0] $end
$var wire 4 C alu_control [3:0] $end
$var parameter 4 D ADD $end
$var parameter 4 E AND $end
$var parameter 4 F COMPLEMENT $end
$var parameter 4 G DECREMENT $end
$var parameter 4 H INCREMENT $end
$var parameter 4 I OR $end
$var parameter 4 J SUB $end
$var parameter 4 K XOR $end
$var reg 32 L alu_result [31:0] $end
$upscope $end
$scope module cu $end
$var wire 6 M controlunit_funct [5:0] $end
$var wire 6 N controlunit_opcode [5:0] $end
$var reg 1 ? controlunit_ALUSrc $end
$var reg 1 & controlunit_MemRead $end
$var reg 1 < controlunit_MemToReg $end
$var reg 1 % controlunit_MemWrite $end
$var reg 1 8 controlunit_RegDst $end
$var reg 1 # controlunit_RegWrite $end
$var reg 4 O controlunit_alu_control [3:0] $end
$upscope $end
$scope module dm $end
$var wire 1 & datamem_MemRead $end
$var wire 1 % datamem_MemWrite $end
$var wire 32 P datamem_address [31:0] $end
$var wire 1 ( datamem_clk $end
$var wire 32 Q datamem_Write [31:0] $end
$var reg 32 R datamem_Read [31:0] $end
$upscope $end
$scope module imem $end
$var wire 32 S inmem_instruction [31:0] $end
$var wire 32 T inmem_address [31:0] $end
$upscope $end
$scope module pc_d $end
$var wire 1 ( clk $end
$var wire 1 ) rst $end
$var reg 32 U pc_out [31:0] $end
$upscope $end
$scope module rf $end
$var wire 5 V regfile_ReadReg1 [4:0] $end
$var wire 5 W regfile_ReadReg2 [4:0] $end
$var wire 1 # regfile_RegWrite $end
$var wire 32 X regfile_WriteData [31:0] $end
$var wire 5 Y regfile_WriteReg [4:0] $end
$var wire 1 ( regfile_clk $end
$var wire 1 ) regfile_rst $end
$var reg 32 Z regfile_ReadData1 [31:0] $end
$var reg 32 [ regfile_ReadData2 [31:0] $end
$upscope $end
$scope module se $end
$var wire 16 \ signextend_in [15:0] $end
$var wire 32 ] signextend_out [31:0] $end
$upscope $end
$upscope $end
$upscope $end
$enddefinitions $end
$comment Show the parameter values. $end
$dumpall
b10 K
b110 J
b11 I
b111 H
b100 G
b0 F
b1 E
b101 D
$end
#0
$dumpvars
b0 ]
b0 \
b0 [
b0 Z
b0 Y
b11111111111111111111111111111111 X
b0 W
b0 V
b0 U
b0 T
b0 S
b0 R
b0 Q
b11111111111111111111111111111111 P
b0 O
b0 N
b0 M
b11111111111111111111111111111111 L
b0 C
b0 B
0A
b0 @
0?
b0 >
b11111111111111111111111111111111 =
0<
b0 ;
b0 :
b0 9
08
b11111111111111111111111111111111 7
b0 6
b0 5
b0 4
b0 3
b0 2
b0 1
b0 0
b0 /
b0 .
b0 -
b0 ,
b0 +
b0 *
0)
0(
b11111111111111111111111111111111 '
0&
0%
b0 $
0#
b0 "
b0 !
$end
#5000
1(
#10000
0(
#15000
1(
#20000
0(
1)
#25000
bx 7
bx X
bx 5
bx @
xA
bx '
bx =
bx L
bx P
b1000 6
b1000 Y
bx $
bx :
bx Q
bx [
bx ;
bx B
bx Z
b101 >
b101 C
b101 O
18
1#
b100000000100000 ,
b100000000100000 ]
b100000000100000 3
b100000000100000 \
b100000 4
b100000 M
b1000 /
b1010 -
b1010 W
b1001 .
b1001 V
b1 1
b1 N
b101001010100100000000100000 "
b101001010100100000000100000 *
b101001010100100000000100000 2
b101001010100100000000100000 S
b100 !
b100 +
b100 0
b100 T
b100 U
1(
#30000
b11110 7
b11110 X
0A
b11110 '
b11110 =
b11110 L
b11110 P
b10100 5
b10100 @
b10100 $
b10100 :
b10100 Q
b10100 [
b1010 ;
b1010 B
b1010 Z
0(
#35000
b101000 7
b101000 X
b1010 5
b1010 @
b101000 '
b101000 =
b101000 L
b101000 P
b1011 6
b1011 Y
b1010 $
b1010 :
b1010 Q
b1010 [
b11110 ;
b11110 B
b11110 Z
b101100000100000 ,
b101100000100000 ]
b101100000100000 3
b101100000100000 \
b1011 /
b1001 -
b1001 W
b1000 .
b1000 V
b101000010010101100000100000 "
b101000010010101100000100000 *
b101000010010101100000100000 2
b101000010010101100000100000 S
b1000 !
b1000 +
b1000 0
b1000 T
b1000 U
1(
#40000
0(
#45000
b111100 7
b111100 X
b101000 5
b101000 @
b111100 '
b111100 =
b111100 L
b111100 P
b1100 6
b1100 Y
b101000 $
b101000 :
b101000 Q
b101000 [
b10100 ;
b10100 B
b10100 Z
b110000000100000 ,
b110000000100000 ]
b110000000100000 3
b110000000100000 \
b1100 /
b1011 -
b1011 W
b1010 .
b1010 V
b101010010110110000000100000 "
b101010010110110000000100000 *
b101010010110110000000100000 2
b101010010110110000000100000 S
b1100 !
b1100 +
b1100 0
b1100 T
b1100 U
1(
#50000
0(
#55000
b1100100 7
b1100100 X
b111100 5
b111100 @
b1100100 '
b1100100 =
b1100100 L
b1100100 P
b1101 6
b1101 Y
b111100 $
b111100 :
b111100 Q
b111100 [
b101000 ;
b101000 B
b101000 Z
b110100000100000 ,
b110100000100000 ]
b110100000100000 3
b110100000100000 \
b1101 /
b1100 -
b1100 W
b1011 .
b1011 V
b101011011000110100000100000 "
b101011011000110100000100000 *
b101011011000110100000100000 2
b101011011000110100000100000 S
b10000 !
b10000 +
b10000 0
b10000 T
b10000 U
1(
#60000
0(
#65000
b10100000 7
b10100000 X
b1100100 5
b1100100 @
b10100000 '
b10100000 =
b10100000 L
b10100000 P
b1110 6
b1110 Y
b1100100 $
b1100100 :
b1100100 Q
b1100100 [
b111100 ;
b111100 B
b111100 Z
b111000000100000 ,
b111000000100000 ]
b111000000100000 3
b111000000100000 \
b1110 /
b1101 -
b1101 W
b1100 .
b1100 V
b101100011010111000000100000 "
b101100011010111000000100000 *
b101100011010111000000100000 2
b101100011010111000000100000 S
b10100 !
b10100 +
b10100 0
b10100 T
b10100 U
1(
#70000
0(
#75000
b100000100 7
b100000100 X
b10100000 5
b10100000 @
b100000100 '
b100000100 =
b100000100 L
b100000100 P
b1111 6
b1111 Y
b10100000 $
b10100000 :
b10100000 Q
b10100000 [
b1100100 ;
b1100100 B
b1100100 Z
b111100000100000 ,
b111100000100000 ]
b111100000100000 3
b111100000100000 \
b1111 /
b1110 -
b1110 W
b1101 .
b1101 V
b101101011100111100000100000 "
b101101011100111100000100000 *
b101101011100111100000100000 2
b101101011100111100000100000 S
b11000 !
b11000 +
b11000 0
b11000 T
b11000 U
1(
#80000
0(
#85000
b110100100 7
b110100100 X
b100000100 5
b100000100 @
b110100100 '
b110100100 =
b110100100 L
b110100100 P
b10000 6
b10000 Y
b100000100 $
b100000100 :
b100000100 Q
b100000100 [
b10100000 ;
b10100000 B
b10100000 Z
b11111111111111111000000000100000 ,
b11111111111111111000000000100000 ]
b1000000000100000 3
b1000000000100000 \
b10000 /
b1111 -
b1111 W
b1110 .
b1110 V
b101110011111000000000100000 "
b101110011111000000000100000 *
b101110011111000000000100000 2
b101110011111000000000100000 S
b11100 !
b11100 +
b11100 0
b11100 T
b11100 U
1(
#90000
0(
#95000
b110100100 7
b110100100 X
b0 5
b0 @
b110100100 '
b110100100 =
b110100100 L
b110100100 P
b10001 6
b10001 Y
b0 $
b0 :
b0 Q
b0 [
b110100100 ;
b110100100 B
b110100100 Z
b11111111111111111000100000100000 ,
b11111111111111111000100000100000 ]
b1000100000100000 3
b1000100000100000 \
b10001 /
b0 -
b0 W
b10000 .
b10000 V
b110000000001000100000100000 "
b110000000001000100000100000 *
b110000000001000100000100000 2
b110000000001000100000100000 S
b100000 !
b100000 +
b100000 0
b100000 T
b100000 U
1(
#100000
0(
#105000
b111000010 7
b111000010 X
b111000010 '
b111000010 =
b111000010 L
b111000010 P
b11110 5
b11110 @
b1000 6
b1000 Y
b11110 $
b11110 :
b11110 Q
b11110 [
b100000000100000 ,
b100000000100000 ]
b100000000100000 3
b100000000100000 \
b1000 /
b1000 -
b1000 W
b10001 .
b10001 V
b110001010000100000000100000 "
b110001010000100000000100000 *
b110001010000100000000100000 2
b110001010000100000000100000 S
b100100 !
b100100 +
b100100 0
b100100 T
b100100 U
1(
#110000
0(
#115000
b111001100 7
b111001100 X
b111001100 '
b111001100 =
b111001100 L
b111001100 P
b1001 6
b1001 Y
b111000010 ;
b111000010 B
b111000010 Z
b1010 5
b1010 @
b100100000100000 ,
b100100000100000 ]
b100100000100000 3
b100100000100000 \
b1001 /
b1001 -
b1001 W
b1000 .
b1000 V
b1010 $
b1010 :
b1010 Q
b1010 [
b101000010010100100000100000 "
b101000010010100100000100000 *
b101000010010100100000100000 2
b101000010010100100000100000 S
b101000 !
b101000 +
b101000 0
b101000 T
b101000 U
1(
#120000
0(
#125000
1A
b0 '
b0 =
b0 L
b0 P
b100000000 9
b100000000 R
b100000000 7
b100000000 X
b1000 6
b1000 Y
b0 ;
b0 B
b0 Z
1&
1<
1?
b101 >
b101 C
b101 O
08
b0 5
b0 @
b0 ,
b0 ]
b0 3
b0 \
b0 4
b0 M
b0 /
b1000 -
b1000 W
b0 .
b0 V
b100 1
b100 N
b111000010 $
b111000010 :
b111000010 Q
b111000010 [
b10000000010000000000000000000 "
b10000000010000000000000000000 *
b10000000010000000000000000000 2
b10000000010000000000000000000 S
b101100 !
b101100 +
b101100 0
b101100 T
b101100 U
1(
#130000
0(
#135000
b1000000000 7
b1000000000 X
b1000000000 9
b1000000000 R
0A
b100 '
b100 =
b100 L
b100 P
b100 5
b100 @
b101 >
b101 C
b101 O
1&
1<
1?
b1001 6
b1001 Y
b100 ,
b100 ]
b100 3
b100 \
b100 4
b100 M
b1001 -
b1001 W
b111001100 $
b111001100 :
b111001100 Q
b111001100 [
b10000000010010000000000000100 "
b10000000010010000000000000100 *
b10000000010010000000000000100 2
b10000000010010000000000000100 S
b110000 !
b110000 +
b110000 0
b110000 T
b110000 U
1(
#140000
0(
#145000
b1100000000 7
b1100000000 X
b1100000000 9
b1100000000 R
b1000 '
b1000 =
b1000 L
b1000 P
b1000 5
b1000 @
b101 >
b101 C
b101 O
1&
1<
1?
b1010 6
b1010 Y
b1000 ,
b1000 ]
b1000 3
b1000 \
b1000 4
b1000 M
b1010 -
b1010 W
b10100 $
b10100 :
b10100 Q
b10100 [
b10000000010100000000000001000 "
b10000000010100000000000001000 *
b10000000010100000000000001000 2
b10000000010100000000000001000 S
b110100 !
b110100 +
b110100 0
b110100 T
b110100 U
1(
#150000
0(
#155000
b10000000000 7
b10000000000 X
b10000000000 9
b10000000000 R
b1100 '
b1100 =
b1100 L
b1100 P
b1100 5
b1100 @
b101 >
b101 C
b101 O
1&
1<
1?
b1011 6
b1011 Y
b1100 ,
b1100 ]
b1100 3
b1100 \
b1100 4
b1100 M
b1011 -
b1011 W
b101000 $
b101000 :
b101000 Q
b101000 [
b10000000010110000000000001100 "
b10000000010110000000000001100 *
b10000000010110000000000001100 2
b10000000010110000000000001100 S
b111000 !
b111000 +
b111000 0
b111000 T
b111000 U
1(
#160000
0(
#165000
b10100000000 7
b10100000000 X
b10100000000 9
b10100000000 R
b10000 '
b10000 =
b10000 L
b10000 P
b10000 5
b10000 @
b101 >
b101 C
b101 O
1&
1<
1?
b1100 6
b1100 Y
b10000 ,
b10000 ]
b10000 3
b10000 \
b10000 4
b10000 M
b1100 -
b1100 W
b111100 $
b111100 :
b111100 Q
b111100 [
b10000000011000000000000010000 "
b10000000011000000000000010000 *
b10000000011000000000000010000 2
b10000000011000000000000010000 S
b111100 !
b111100 +
b111100 0
b111100 T
b111100 U
1(
#170000
0(
#175000
b11000000000 7
b11000000000 X
b11000000000 9
b11000000000 R
b10100 '
b10100 =
b10100 L
b10100 P
b10100 5
b10100 @
b101 >
b101 C
b101 O
1&
1<
1?
b1101 6
b1101 Y
b10100 ,
b10100 ]
b10100 3
b10100 \
b10100 4
b10100 M
b1101 -
b1101 W
b1100100 $
b1100100 :
b1100100 Q
b1100100 [
b10000000011010000000000010100 "
b10000000011010000000000010100 *
b10000000011010000000000010100 2
b10000000011010000000000010100 S
b1000000 !
b1000000 +
b1000000 0
b1000000 T
b1000000 U
1(
#180000
0(
#185000
b11100000000 7
b11100000000 X
b11100000000 9
b11100000000 R
b11000 '
b11000 =
b11000 L
b11000 P
b11000 5
b11000 @
b101 >
b101 C
b101 O
1&
1<
1?
b1110 6
b1110 Y
b11000 ,
b11000 ]
b11000 3
b11000 \
b11000 4
b11000 M
b1110 -
b1110 W
b10100000 $
b10100000 :
b10100000 Q
b10100000 [
b10000000011100000000000011000 "
b10000000011100000000000011000 *
b10000000011100000000000011000 2
b10000000011100000000000011000 S
b1000100 !
b1000100 +
b1000100 0
b1000100 T
b1000100 U
1(
#190000
0(
#195000
b100000000000 7
b100000000000 X
b100000000000 9
b100000000000 R
b11100 '
b11100 =
b11100 L
b11100 P
b11100 5
b11100 @
b101 >
b101 C
b101 O
1&
1<
1?
b1111 6
b1111 Y
b11100 ,
b11100 ]
b11100 3
b11100 \
b11100 4
b11100 M
b1111 -
b1111 W
b100000100 $
b100000100 :
b100000100 Q
b100000100 [
b10000000011110000000000011100 "
b10000000011110000000000011100 *
b10000000011110000000000011100 2
b10000000011110000000000011100 S
b1001000 !
b1001000 +
b1001000 0
b1001000 T
b1001000 U
1(
#200000
0(
#205000
b100100000000 7
b100100000000 X
b100100000000 9
b100100000000 R
b100000 '
b100000 =
b100000 L
b100000 P
b100000 5
b100000 @
b101 >
b101 C
b101 O
1&
1<
1?
b10000 6
b10000 Y
b100000 ,
b100000 ]
b100000 3
b100000 \
b100000 4
b100000 M
b10000 -
b10000 W
b110100100 $
b110100100 :
b110100100 Q
b110100100 [
b10000000100000000000000100000 "
b10000000100000000000000100000 *
b10000000100000000000000100000 2
b10000000100000000000000100000 S
b1001100 !
b1001100 +
b1001100 0
b1001100 T
b1001100 U
1(
#210000
0(
