Task4-6/regfile.v
module regfile(
    input wire clk, rst,
    input wire RegWrite,
    input wire [4:0] ReadReg1, ReadReg2, WriteReg, 
    input wire [31:0] WriteData,
    output reg [31:0] ReadData1, ReadData2
);

reg [31:0] Regs [0:31];
initial begin
    Regs[0] = 32'b0;
end

always @(posedge clk) begin
    if (!rst) begin
        Regs[0] <= 32'b0;
    end
    else if (RegWrite) begin
        if (WriteReg != 5'b00000) begin
            Regs[WriteReg] <= WriteData;
        end
    end
end

always @(*) begin
    ReadData1 = (ReadReg1 == 5'b00000) ? 32'b0 : Regs[ReadReg1];
    ReadData2 = (ReadReg2 == 5'b00000) ? 32'b0 : Regs[ReadReg2];
end
endmodule

Task4-6/tb/regfile_tb.v
`timescale 1ns / 1ps
`include "../regfile.v"
module regfile_tb;
    // Inputs
    reg clk;
    reg rst;
    reg RegWrite;
    reg [4:0] ReadReg1, ReadReg2, WriteReg;
    reg [31:0] WriteData;
    
    // Outputs
    wire [31:0] ReadData1, ReadData2;
    
    // Instantiate the register file module
    regfile regfile_inst (
        .clk(clk),
        .rst(rst),
        .RegWrite(RegWrite),
        .ReadReg1(ReadReg1),
        .ReadReg2(ReadReg2),
        .WriteReg(WriteReg),
        .WriteData(WriteData),
        .ReadData1(ReadData1),
        .ReadData2(ReadData2)
    );
    
    // Clock generation
    initial begin
        clk = 0;
        forever #5 clk = ~clk; // 10ns clock period
    end
    
    // Test procedure
    initial begin
        $dumpfile("../vcd/regfile.vcd");
        $dumpvars(0, regfile_tb);
        // Initialize inputs
        rst = 1;
        RegWrite = 0;
        ReadReg1 = 5'b0;
        ReadReg2 = 5'b0;
        WriteReg = 5'b0;
        WriteData = 32'h0;
        
        // Monitor outputs
        $monitor("Time=%0t clk=%b rst=%b RegWrite=%b WriteReg=%d WriteData=%h ReadReg1=%d ReadData1=%h ReadReg2=%d ReadData2=%h", 
                 $time, clk, rst, RegWrite, WriteReg, WriteData, ReadReg1, ReadData1, ReadReg2, ReadData2);
        
        // Test 1: Write to register 1 (before reset)
        #10;
        RegWrite = 1;
        WriteReg = 5'd1;
        WriteData = 32'hDEADBEEF;
        #10; // Wait for posedge clk to write
        
        // Test 2: Reset (only Regs[0] should be 0)
        #10;
        rst = 0; // Assert reset
        #10;
        rst = 1; // Deassert reset
        ReadReg1 = 5'd0;
        ReadReg2 = 5'd1;
        #10; // Check ReadData1=0, ReadData2=0xDEADBEEF (unchanged)
        
        // Test 3: Read from register 0 and 1
        #10;
        RegWrite = 0;
        ReadReg1 = 5'd0;
        ReadReg2 = 5'd1;
        #10; // Check ReadData1=0, ReadData2=0xDEADBEEF
        
        // Test 4: Write to register 31
        #10;
        RegWrite = 1;
        WriteReg = 5'd31;
        WriteData = 32'h12345678;
        #10; // Wait for posedge clk to write
        
        // Test 5: Read from register 31 and uninitialized register 2
        #10;
        RegWrite = 0;
        ReadReg1 = 5'd31;
        ReadReg2 = 5'd2;
        #10; // Check ReadData1=0x12345678, ReadData2=x (uninitialized)
        
        // Test 6: Attempt to write to register 0 (should not change)
        #10;
        RegWrite = 1;
        WriteReg = 5'd0;
        WriteData = 32'hFFFFFFFF;
        #10;
        ReadReg1 = 5'd0;
        ReadReg2 = 5'd31;
        #10; // Check ReadData1=0, ReadData2=0x12345678
        
        // Test 7: Attempt write with RegWrite=0 (no change)
        #10;
        RegWrite = 0;
        WriteReg = 5'd3;
        WriteData = 32'hA5A5A5A5;
        #10;
        ReadReg1 = 5'd3;
        ReadReg2 = 5'd1;
        #10; // Check ReadData1=x (unwritten), ReadData2=0xDEADBEEF
        
        // Test 8: Write and read same register in same cycle
        #10;
        RegWrite = 1;
        WriteReg = 5'd4;
        WriteData = 32'h5555AAAA;
        ReadReg1 = 5'd4;
        ReadReg2 = 5'd4;
        #10; // Check ReadData1/2=x (old value, since write is synchronous)
        #10;
        RegWrite = 0;
        #10; // Check ReadData1/2=0x5555AAAA after write
        
        // Finish simulation
        #10;
        $finish;
    end
endmodule

Task4-6/vcd/regfile.vcd
$date
    May 15, 2025  17:53:57
$end
$version
    TOOL:	xmsim(64)	23.03-s007
$end
$timescale
    1 ps
$end

$scope module regfile_tb $end
$var reg       1 !    clk $end
$var reg       1 "    rst $end
$var reg       1 #    RegWrite $end
$var reg       5 $    ReadReg1 [4:0] $end
$var reg       5 %    ReadReg2 [4:0] $end
$var reg       5 &    WriteReg [4:0] $end
$var reg      32 '    WriteData [31:0] $end
$var wire     32 (    ReadData1 [31:0] $end
$var wire     32 )    ReadData2 [31:0] $end

$scope module regfile_inst $end
$var wire      1 *    clk  $end
$var wire      1 +    rst  $end
$var wire      1 ,    RegWrite  $end
$var wire      5 -    ReadReg1 [4:0] $end
$var wire      5 .    ReadReg2 [4:0] $end
$var wire      5 /    WriteReg [4:0] $end
$var wire     32 0    WriteData [31:0] $end
$var reg      32 1    ReadData1 [31:0] $end
$var reg      32 2    ReadData2 [31:0] $end
$var reg      32 3    Regs[0] [31:0] $end
$var reg      32 4    Regs[1] [31:0] $end
$var reg      32 5    Regs[2] [31:0] $end
$var reg      32 6    Regs[3] [31:0] $end
$var reg      32 7    Regs[4] [31:0] $end
$var reg      32 8    Regs[5] [31:0] $end
$var reg      32 9    Regs[6] [31:0] $end
$var reg      32 :    Regs[7] [31:0] $end
$var reg      32 ;    Regs[8] [31:0] $end
$var reg      32 <    Regs[9] [31:0] $end
$var reg      32 =    Regs[10] [31:0] $end
$var reg      32 >    Regs[11] [31:0] $end
$var reg      32 ?    Regs[12] [31:0] $end
$var reg      32 @    Regs[13] [31:0] $end
$var reg      32 A    Regs[14] [31:0] $end
$var reg      32 B    Regs[15] [31:0] $end
$var reg      32 C    Regs[16] [31:0] $end
$var reg      32 D    Regs[17] [31:0] $end
$var reg      32 E    Regs[18] [31:0] $end
$var reg      32 F    Regs[19] [31:0] $end
$var reg      32 G    Regs[20] [31:0] $end
$var reg      32 H    Regs[21] [31:0] $end
$var reg      32 I    Regs[22] [31:0] $end
$var reg      32 J    Regs[23] [31:0] $end
$var reg      32 K    Regs[24] [31:0] $end
$var reg      32 L    Regs[25] [31:0] $end
$var reg      32 M    Regs[26] [31:0] $end
$var reg      32 N    Regs[27] [31:0] $end
$var reg      32 O    Regs[28] [31:0] $end
$var reg      32 P    Regs[29] [31:0] $end
$var reg      32 Q    Regs[30] [31:0] $end
$var reg      32 R    Regs[31] [31:0] $end
$upscope $end

$upscope $end

$enddefinitions $end
$dumpvars
0!
1"
0#
b0 $
b0 %
b0 &
b0 '
b0 (
b0 )
0*
1+
0,
b0 -
b0 .
b0 /
b0 0
b0 1
b0 2
b0 3
bx 4
bx 5
bx 6
bx 7
bx 8
bx 9
bx :
bx ;
bx <
bx =
bx >
bx ?
bx @
bx A
bx B
bx C
bx D
bx E
bx F
bx G
bx H
bx I
bx J
bx K
bx L
bx M
bx N
bx O
bx P
bx Q
bx R
$end
#5000
1!
1*
#10000
1#
b1 &
b11011110101011011011111011101111 '
0!
0*
b11011110101011011011111011101111 0
b1 /
1,
#15000
1!
1*
b11011110101011011011111011101111 4
#20000
0!
0*
#25000
1!
1*
#30000
0"
0!
0*
0+
#35000
1!
1*
#40000
1"
b1 %
0!
0*
b1 .
1+
b11011110101011011011111011101111 2
b11011110101011011011111011101111 )
#45000
1!
1*
#50000
0!
0*
#55000
1!
1*
#60000
0#
0!
0*
0,
#65000
1!
1*
#70000
0!
0*
#75000
1!
1*
#80000
1#
b11111 &
b10010001101000101011001111000 '
0!
0*
b10010001101000101011001111000 0
b11111 /
1,
#85000
1!
1*
b10010001101000101011001111000 R
#90000
0!
0*
#95000
1!
1*
#100000
0#
b11111 $
b10 %
0!
0*
b10 .
b11111 -
0,
b10010001101000101011001111000 1
bx 2
bx )
b10010001101000101011001111000 (
#105000
1!
1*
#110000
0!
0*
#115000
1!
1*
#120000
1#
b0 &
b11111111111111111111111111111111 '
0!
0*
b11111111111111111111111111111111 0
b0 /
1,
#125000
1!
1*
#130000
b0 $
b11111 %
0!
0*
b11111 .
b0 -
b0 1
b10010001101000101011001111000 2
b10010001101000101011001111000 )
b0 (
#135000
1!
1*
#140000
0!
0*
#145000
1!
1*
#150000
0#
b11 &
b10100101101001011010010110100101 '
0!
0*
b10100101101001011010010110100101 0
b11 /
0,
#155000
1!
1*
#160000
b11 $
b1 %
0!
0*
b1 .
b11 -
bx 1
b11011110101011011011111011101111 2
b11011110101011011011111011101111 )
bx (
#165000
1!
1*
#170000
0!
0*
#175000
1!
1*
#180000
1#
b100 &
b1010101010101011010101010101010 '
b100 $
b100 %
0!
0*
b100 .
b100 -
b1010101010101011010101010101010 0
b100 /
1,
bx 2
bx )
#185000
1!
1*
b1010101010101011010101010101010 7
b1010101010101011010101010101010 1
b1010101010101011010101010101010 2
b1010101010101011010101010101010 )
b1010101010101011010101010101010 (
#190000
0!
0*
#195000
1!
1*
#200000
0#
0!
0*
0,
