RAM/basic/synchronous/basic_ram.v
module basic_ram (
    input clk, we,
    input [3:0] addr,
    input [7:0] in,
    output reg [7:0] out
);

reg [7:0] mem [15:0];

always @(posedge clk) begin
    if (we)
        mem [addr] <= in;
    else
        out <= mem[addr];
end
endmodule

RAM/basic/synchronous/basic_ram_tb.v
`timescale 1ps/1ps

module basic_ram_tb;
    reg clk, we;
    reg [3:0] addr;
    reg [7:0] in;
    wire [7:0] out;

    basic_ram bsr(
        .clk(clk),
        .we(we),
        .addr(addr),
        .in(in),
        .out(out)
    );

always #5 clk = ~clk;

initial begin
    $dumpfile("basic_ram_tb.vcd");
    $dumpvars(0, basic_ram_tb);

    clk = 0;
    //write
    we = 1;
    addr = 4'b0000; in = 8'h81; #10;
    addr = 4'b0001; in = 8'hEA; #10;
    addr = 4'b0010; in = 8'hFF; #10;

    //read
    we = 0;
    addr = 4'b0000; #10;
    addr = 4'b0001; #10;
    addr = 4'b0010; #10;

    $finish;
end
endmodule

RAM/basic/synchronous/basic_ram_tb.vcd
$date
	Sat Mar  8 22:15:14 2025
$end
$version
	Icarus Verilog
$end
$timescale
	1ps
$end
$scope module basic_ram_tb $end
$var wire 8 ! out [7:0] $end
$var reg 4 " addr [3:0] $end
$var reg 1 # clk $end
$var reg 8 $ in [7:0] $end
$var reg 1 % we $end
$scope module bsr $end
$var wire 4 & addr [3:0] $end
$var wire 1 # clk $end
$var wire 8 ' in [7:0] $end
$var wire 1 % we $end
$var reg 8 ( out [7:0] $end
$upscope $end
$upscope $end
$enddefinitions $end
$comment Show the parameter values. $end
$dumpall
$end
#0
$dumpvars
bx (
b10000001 '
b0 &
1%
b10000001 $
0#
b0 "
bx !
$end
#5
1#
#10
0#
b11101010 $
b11101010 '
b1 "
b1 &
#15
1#
#20
0#
b11111111 $
b11111111 '
b10 "
b10 &
#25
1#
#30
0#
b0 "
b0 &
0%
#35
b10000001 !
b10000001 (
1#
#40
0#
b1 "
b1 &
#45
b11101010 !
b11101010 (
1#
#50
0#
b10 "
b10 &
#55
b11111111 !
b11111111 (
1#
