Task4-6/ALU/alu.v
module alu (
  input signed [31:0] operand1, operand2,
  input [2:0] aluop,
  output reg signed [31:0] alu_out,
  output reg add_sub_overflow
);

reg signed [31:0] alu_tmp;

parameter COMPLEMENT = 3'b000;
parameter AND        = 3'b001;
parameter XOR        = 3'b010;
parameter OR         = 3'b011;
parameter DECREMENT  = 3'b100;
parameter ADD        = 3'b101;
parameter SUB        = 3'b110;
parameter INCREMENT  = 3'b111;

always @(*) begin
  add_sub_overflow = 0;  // reset overflow flag
  case(aluop)
    COMPLEMENT  : alu_tmp = ~(operand1)+1;
    AND         : alu_tmp = operand1 & operand2;
    XOR         : alu_tmp = operand1 ^ operand2;
    OR          : alu_tmp = operand1 | operand2;
    DECREMENT   : alu_tmp = operand1 - 1;
    ADD         : begin
      alu_tmp = operand1 + operand2;
      add_sub_overflow = (operand1[31] == operand2[31]) && (alu_tmp[31] != operand1[31]);
    end
    SUB         : begin
      alu_tmp = operand1 - operand2;
      add_sub_overflow = (operand1[31] != operand2[31]) && (alu_tmp[31] != operand1[31]);
    end
    INCREMENT   : alu_tmp = operand1 + 1;
    default     : alu_tmp = 0;
  endcase
  alu_out = alu_tmp;
end

endmodule

Task4-6/ALU/alu_tb.v
`timescale 1ps/1ps

module alu_tb;
  reg signed [31:0] operand1, operand2;
  reg [2:0] alu_op;
  wire signed [31:0] alu_out;
  wire add_sub_overflow;

  alu uut(
    .operand1(operand1),
    .operand2(operand2),
    .aluop(alu_op),
    .alu_out(alu_out),
    .add_sub_overflow(add_sub_overflow)
  );
  initial begin
    $dumpfile("alu_tb.vcd");
    $dumpvars(0, alu_tb);
    //operand1 = 0000_0000_0000_0000_0000_0000_0010_0000
    //operand2 = 0000_0000_0000_0000_0000_0000_0010_0010
    operand1 = 32'd32;
    operand2 = 32'd34;
    alu_op = 3'b000; #10; //FFFFFFE0
    alu_op = 3'b001; #10; //00000020
    alu_op = 3'b010; #10; //00000002
    alu_op = 3'b011; #10; //00000022
    alu_op = 3'b100; #10; //0000001F
    alu_op = 3'b101; #10; //00000042
    alu_op = 3'b110; #10; //FFFFFFFE
    alu_op = 3'b111; #10; //00000021
    //check overflow
    //ADD
    // ✅ ADD overflow: 0x7FFFFFFF + 0x00000001 = overflow (2147483647 + 1)
    operand1 = 32'h7FFFFFFF;  // +2147483647
    operand2 = 32'h00000001;  // +1
    alu_op = 3'b101;           // ADD
    #10;

    // ✅ SUB overflow: 0x80000000 - 0xFFFFFFFF = overflow (-2147483648 - (-1))
    operand1 = 32'h7FFFFFFF;  // 2147483647
    operand2 = 32'hFFFFFFFF;  // -1    alu_op = 3'b110;           // SUB
    alu_op = 3'b110;
    #10;    
    $finish;
 end
endmodule

Task4-6/ALU/alu_tb.vcd
$date
	Sun May 11 22:36:49 2025
$end
$version
	Icarus Verilog
$end
$timescale
	1ps
$end
$scope module alu_tb $end
$var wire 32 ! alu_out [31:0] $end
$var wire 1 " add_sub_overflow $end
$var reg 3 # alu_op [2:0] $end
$var reg 32 $ operand1 [31:0] $end
$var reg 32 % operand2 [31:0] $end
$scope module uut $end
$var wire 3 & aluop [2:0] $end
$var wire 32 ' operand1 [31:0] $end
$var wire 32 ( operand2 [31:0] $end
$var parameter 3 ) ADD $end
$var parameter 3 * AND $end
$var parameter 3 + COMPLEMENT $end
$var parameter 3 , DECREMENT $end
$var parameter 3 - INCREMENT $end
$var parameter 3 . OR $end
$var parameter 3 / SUB $end
$var parameter 3 0 XOR $end
$var reg 1 " add_sub_overflow $end
$var reg 32 1 alu_out [31:0] $end
$var reg 32 2 alu_tmp [31:0] $end
$upscope $end
$upscope $end
$enddefinitions $end
$comment Show the parameter values. $end
$dumpall
b10 0
b110 /
b11 .
b111 -
b100 ,
b0 +
b1 *
b101 )
$end
#0
$dumpvars
b11111111111111111111111111100000 2
b11111111111111111111111111100000 1
b100010 (
b100000 '
b0 &
b100010 %
b100000 $
b0 #
0"
b11111111111111111111111111100000 !
$end
#10
b100000 !
b100000 1
b100000 2
b1 #
b1 &
#20
b10 !
b10 1
b10 2
b10 #
b10 &
#30
b100010 !
b100010 1
b100010 2
b11 #
b11 &
#40
b11111 !
b11111 1
b11111 2
b100 #
b100 &
#50
b1000010 !
b1000010 1
b1000010 2
b101 #
b101 &
#60
b11111111111111111111111111111110 !
b11111111111111111111111111111110 1
b11111111111111111111111111111110 2
b110 #
b110 &
#70
b100001 !
b100001 1
b100001 2
b111 #
b111 &
#80
b10000000000000000000000000000000 !
b10000000000000000000000000000000 1
1"
b10000000000000000000000000000000 2
b101 #
b101 &
b1 %
b1 (
b1111111111111111111111111111111 $
b1111111111111111111111111111111 '
#90
1"
b110 #
b110 &
b11111111111111111111111111111111 %
b11111111111111111111111111111111 (
