RAM/dual_port/asynchronous/dual_port_ram.v
module dual_port_ram (
    input clk, we_a, we_b,
    input [3:0] addr_a, addr_b,
    input [7:0] din_a, din_b,
    output [7:0] dout_a, dout_b
);

reg [7:0] mem [15:0];
always @(posedge clk) begin
    if (we_a)
        mem[addr_a] <= din_a;
    if (we_b)
        mem[addr_b] <= din_b;
end
assign dout_a = mem[addr_a];   
assign dout_b = mem[addr_b];

endmodule

RAM/dual_port/asynchronous/dual_port_ram_tb.v
`timescale 1ps/1ps

module dual_port_ram_tb;
    reg clk, we_a, we_b;
    reg [3:0] addr_a, addr_b;
    reg [7:0] din_a, din_b;
    wire [7:0] dout_a, dout_b;

    dual_port_ram dpr(
        .clk(clk),
        .we_a(we_a),
        .we_b(we_b),
        .addr_a(addr_a),
        .addr_b(addr_b),
        .din_a(din_a),
        .din_b(din_b),
        .dout_a(dout_a),
        .dout_b(dout_b)
    );

always #5 clk = ~clk;

initial begin
    $dumpfile("dual_port_ram_tb.vcd");
    $dumpvars(0, dual_port_ram_tb);

    clk = 0;
    //write a and b
    we_a = 1; 
    addr_a = 4'b0000; din_a = 8'hEA; #10;
    addr_a = 4'b0010; din_a = 8'h12; #10;
    we_b = 1;
    addr_b = 4'b0100; din_b = 8'h32; addr_a = 4'b0011; din_a = 8'h11; #10;
    addr_b = 4'b0111; din_b = 8'hFF; addr_a = 4'b1000; din_a = 8'h00; #10;
    //read a and write b
    we_a = 0;
    addr_b = 4'b1001; din_b = 8'h21; addr_a = 4'b0000; #1;
    addr_b = 4'b1111; din_b = 8'hAA; addr_a = 4'b0010; #1;
    //read b and read a
    we_b = 0;
    addr_b = 4'b0100; addr_a = 4'b0011; #1;
    addr_b = 4'b0111; addr_a = 4'b1000; #1;
    //read b
    addr_b = 4'b1001; #1;
    addr_b = 4'b1111; #1;

    $finish;
end
endmodule

RAM/dual_port/asynchronous/dual_port_ram_tb.vcd
$date
	Sat Mar  8 23:10:08 2025
$end
$version
	Icarus Verilog
$end
$timescale
	1ps
$end
$scope module dual_port_ram_tb $end
$var wire 8 ! dout_b [7:0] $end
$var wire 8 " dout_a [7:0] $end
$var reg 4 # addr_a [3:0] $end
$var reg 4 $ addr_b [3:0] $end
$var reg 1 % clk $end
$var reg 8 & din_a [7:0] $end
$var reg 8 ' din_b [7:0] $end
$var reg 1 ( we_a $end
$var reg 1 ) we_b $end
$scope module dpr $end
$var wire 4 * addr_a [3:0] $end
$var wire 4 + addr_b [3:0] $end
$var wire 1 % clk $end
$var wire 8 , din_a [7:0] $end
$var wire 8 - din_b [7:0] $end
$var wire 8 . dout_a [7:0] $end
$var wire 8 / dout_b [7:0] $end
$var wire 1 ( we_a $end
$var wire 1 ) we_b $end
$upscope $end
$upscope $end
$enddefinitions $end
$comment Show the parameter values. $end
$dumpall
$end
#0
$dumpvars
bx /
bx .
bx -
b11101010 ,
bx +
b0 *
x)
1(
bx '
b11101010 &
0%
bx $
b0 #
bx "
bx !
$end
#5
b11101010 "
b11101010 .
1%
#10
0%
b10010 &
b10010 ,
bx "
bx .
b10 #
b10 *
#15
b10010 "
b10010 .
1%
#20
0%
b10001 &
b10001 ,
bx "
bx .
b11 #
b11 *
b110010 '
b110010 -
b100 $
b100 +
1)
#25
b110010 !
b110010 /
b10001 "
b10001 .
1%
#30
0%
b0 &
b0 ,
bx "
bx .
b1000 #
b1000 *
b11111111 '
b11111111 -
bx !
bx /
b111 $
b111 +
#35
b11111111 !
b11111111 /
b0 "
b0 .
1%
#40
0%
b11101010 "
b11101010 .
b0 #
b0 *
b100001 '
b100001 -
bx !
bx /
b1001 $
b1001 +
0(
#41
b10010 "
b10010 .
b10 #
b10 *
b10101010 '
b10101010 -
b1111 $
b1111 +
#42
b10001 "
b10001 .
b11 #
b11 *
b110010 !
b110010 /
b100 $
b100 +
0)
#43
b0 "
b0 .
b1000 #
b1000 *
b11111111 !
b11111111 /
b111 $
b111 +
#44
bx !
bx /
b1001 $
b1001 +
#45
b1111 $
b1111 +
1%
