counter4bit/counter4bit.v
module counter4bit (
    input clk, rst, up_down,
    output reg [3:0] result
);

always @(posedge clk) begin
    if (rst)
        result <= 4'b0000;
    else
        if (up_down == 1'b0) begin
            result <= result + 1'b1;
        end
        else    
            result <= result - 1'b1;
end
    
endmodule

counter4bit/counter4bit_tb.v
`timescale 1ps/1ps

module counter4bit_tb;
    reg clk, rst, up_down;
    wire [3:0] result;

    counter4bit ct4(
        .clk(clk),
        .rst(rst),
        .up_down(up_down),
        .result(result)
    );

always #5 clk = ~clk;

initial begin
    $dumpfile("counter4bit_tb.vcd");
    $dumpvars(0, counter4bit_tb);

    clk = 0; #10;
    rst = 1; #10;
    rst = 0; up_down = 0; #200;
    up_down = 1; #200;

    $finish;
end
endmodule

counter4bit/counter4bit_tb.vcd
$date
	Thu Mar  6 22:16:42 2025
$end
$version
	Icarus Verilog
$end
$timescale
	1ps
$end
$scope module counter4bit_tb $end
$var wire 4 ! result [3:0] $end
$var reg 1 " clk $end
$var reg 1 # rst $end
$var reg 1 $ up_down $end
$scope module ct4 $end
$var wire 1 " clk $end
$var wire 1 # rst $end
$var wire 1 $ up_down $end
$var reg 4 % result [3:0] $end
$upscope $end
$upscope $end
$enddefinitions $end
$comment Show the parameter values. $end
$dumpall
$end
#0
$dumpvars
bx %
x$
x#
0"
bx !
$end
#5
1"
#10
0"
1#
#15
b0 !
b0 %
1"
#20
0"
0$
0#
#25
b1 !
b1 %
1"
#30
0"
#35
b10 !
b10 %
1"
#40
0"
#45
b11 !
b11 %
1"
#50
0"
#55
b100 !
b100 %
1"
#60
0"
#65
b101 !
b101 %
1"
#70
0"
#75
b110 !
b110 %
1"
#80
0"
#85
b111 !
b111 %
1"
#90
0"
#95
b1000 !
b1000 %
1"
#100
0"
#105
b1001 !
b1001 %
1"
#110
0"
#115
b1010 !
b1010 %
1"
#120
0"
#125
b1011 !
b1011 %
1"
#130
0"
#135
b1100 !
b1100 %
1"
#140
0"
#145
b1101 !
b1101 %
1"
#150
0"
#155
b1110 !
b1110 %
1"
#160
0"
#165
b1111 !
b1111 %
1"
#170
0"
#175
b0 !
b0 %
1"
#180
0"
#185
b1 !
b1 %
1"
#190
0"
#195
b10 !
b10 %
1"
#200
0"
#205
b11 !
b11 %
1"
#210
0"
#215
b100 !
b100 %
1"
#220
0"
1$
#225
b11 !
b11 %
1"
#230
0"
#235
b10 !
b10 %
1"
#240
0"
#245
b1 !
b1 %
1"
#250
0"
#255
b0 !
b0 %
1"
#260
0"
#265
b1111 !
b1111 %
1"
#270
0"
#275
b1110 !
b1110 %
1"
#280
0"
#285
b1101 !
b1101 %
1"
#290
0"
#295
b1100 !
b1100 %
1"
#300
0"
#305
b1011 !
b1011 %
1"
#310
0"
#315
b1010 !
b1010 %
1"
#320
0"
#325
b1001 !
b1001 %
1"
#330
0"
#335
b1000 !
b1000 %
1"
#340
0"
#345
b111 !
b111 %
1"
#350
0"
#355
b110 !
b110 %
1"
#360
0"
#365
b101 !
b101 %
1"
#370
0"
#375
b100 !
b100 %
1"
#380
0"
#385
b11 !
b11 %
1"
#390
0"
#395
b10 !
b10 %
1"
#400
0"
#405
b1 !
b1 %
1"
#410
0"
#415
b0 !
b0 %
1"
