ALU/ALU.v
module ALU (
    input [3:0] a, b,
    input [2:0] sel,
    output reg [4:0] out
);

always @(*) begin
    if (sel == 3'b000)
        out = a + b;
    else if (sel == 3'b001)
        out = a + 4'b0001;
    else if (sel == 3'b010)
        out = a - b;
    else if (sel == 3'b011)
        out = a - 4'b0001;
    else if (sel == 3'b100)
        out = a & b;
    else if (sel == 3'b101)
        out = ~(a & b);
    else if (sel == 3'b110)
        out = a | b;
    else if (sel == 3'b111)
        out = a ^ b;
    else
        out = 4'b0000;
end // always @ (*)
   endmodule

ALU/ALU_tb.v
`timescale 1ps/1ps

module ALU_tb;
    reg [3:0] a, b;
    reg [2:0] sel;
    wire [4:0] out;

    ALU ALU_inst (
        .a(a),
        .b(b),
        .sel(sel),
        .out(out)
    );

initial begin
    $dumpfile("ALU_tb.vcd");
    $dumpvars(0, ALU_tb);

    a = 4'b1011; b = 4'b0111; sel = 3'b000; #10; 
    a = 4'b1011; b = 4'b0111; sel = 3'b001; #10;
    a = 4'b1011; b = 4'b0111; sel = 3'b010; #10;       
    a = 4'b1011; b = 4'b0111; sel = 3'b011; #10;
    a = 4'b1011; b = 4'b0111; sel = 3'b100; #10;
    a = 4'b1011; b = 4'b0111; sel = 3'b101; #10;
    a = 4'b1011; b = 4'b0111; sel = 3'b110; #10;
    a = 4'b1011; b = 4'b0111; sel = 3'b111; #10;

    $finish;
end

endmodule

ALU/ALU_tb.vcd
$date
	Fri Mar  7 20:10:52 2025
$end
$version
	Icarus Verilog
$end
$timescale
	1ps
$end
$scope module ALU_tb $end
$var wire 5 ! out [4:0] $end
$var reg 4 " a [3:0] $end
$var reg 4 # b [3:0] $end
$var reg 3 $ sel [2:0] $end
$scope module ALU_inst $end
$var wire 4 % a [3:0] $end
$var wire 4 & b [3:0] $end
$var wire 3 ' sel [2:0] $end
$var reg 5 ( out [4:0] $end
$upscope $end
$upscope $end
$enddefinitions $end
$comment Show the parameter values. $end
$dumpall
$end
#0
$dumpvars
b10010 (
b0 '
b111 &
b1011 %
b0 $
b111 #
b1011 "
b10010 !
$end
#10
b1100 !
b1100 (
b1 $
b1 '
#20
b100 !
b100 (
b10 $
b10 '
#30
b1010 !
b1010 (
b11 $
b11 '
#40
b11 !
b11 (
b100 $
b100 '
#50
b11100 !
b11100 (
b101 $
b101 '
#60
b1111 !
b1111 (
b110 $
b110 '
#70
b1100 !
b1100 (
b111 $
b111 '
