OnClass/moore.v
module fsm_moore(
    input clk, rst,
    input [2:0] mssv_moore,
    output reg [1:0] done_moore
);
    reg [2:0] presentstate, nextstate;
    parameter S0 = 3'd0;
    parameter S1 = 3'd1;
    parameter S2 = 3'd2;
    parameter S3 = 3'd3;
    parameter S4 = 4'd4;
always @(posedge clk or posedge rst) begin
    if (rst)
        presentstate <= S0;
    else
        presentstate <= nextstate;
end
always @(*) begin
    case (presentstate)
        S0 : begin
          done_moore = 2'b00;
            if (mssv_moore == 3'b000)
                nextstate = S1;
            else
                nextstate = S0;  
        end 
        S1 : begin
            done_moore = 2'b00;
            if (mssv_moore == 3'b110) 
                nextstate = S2;
            else if (mssv_moore == 3'b000)
                nextstate = S1;
            else    
                nextstate = S0;
        end
        S2 : begin
            done_moore = 2'b00;
            if (mssv_moore == 3'b000) 
                nextstate = S3;
            else    
                nextstate = S0;
        end
        S3 : begin
            done_moore = 2'b00;
            if (mssv_moore == 3'b110)
                nextstate = S4;
            else if (mssv_moore == 3'b000)
                nextstate = S1;
            else
                nextstate = S0;
        end
        S4 : begin
            if (mssv_moore % 2 == 0) 
                done_moore = 2'b11; 
            else if (mssv_moore %2 != 0)
                done_moore = 2'b10; 

            if (mssv_moore == 3'b000)
                nextstate = S3;
            else 
                nextstate = S4;
        end
        default: begin
            nextstate = S0;
            done_moore = 2'b00;
        end
    endcase    
end
endmodule



module fsm_moore_tb;
    reg clk, rst;
    reg [2:0] mssv_moore;
    wire [1:0] done_moore;

    fsm_moore uut (
        .clk(clk),
        .rst(rst),
        .mssv_moore(mssv_moore),
        .done_moore(done_moore)
    );

    // Clock generation
    always #5 clk = ~clk;

    initial begin

        $dumpfile("moore.vcd");
        $dumpvars(0, fsm_moore_tb);
       
        clk = 0;
        rst = 1;
        mssv_moore = 3'b000;
        
        
        #10 rst = 0;


        #10 mssv_moore = 3'b000; 
        #10 mssv_moore = 3'b110; 
        #10 mssv_moore = 3'b000;
        #10 mssv_moore = 3'b110; 
        
        #10 mssv_moore = 3'b000; 
        #10 mssv_moore = 3'b110; 
        #10 mssv_moore = 3'b000; 
        #10 mssv_moore = 3'b111; 

        #10 mssv_moore = 3'b000; 
        #10 mssv_moore = 3'b110; 
        #10 mssv_moore = 3'b000; 
        #10 mssv_moore = 3'b001; 

        #10 mssv_moore = 3'b000; 
        #10 mssv_moore = 3'b110; 
        #10 mssv_moore = 3'b000; 
        #10 mssv_moore = 3'b010; 
        
        #20 $finish;
    end
endmodule

OnClass/moore.vcd
$date
	Sat Apr  5 11:02:50 2025
$end
$version
	Icarus Verilog
$end
$timescale
	1s
$end
$scope module fsm_moore_tb $end
$var wire 2 ! done_moore [1:0] $end
$var reg 1 " clk $end
$var reg 3 # mssv_moore [2:0] $end
$var reg 1 $ rst $end
$scope module uut $end
$var wire 1 " clk $end
$var wire 3 % mssv_moore [2:0] $end
$var wire 1 $ rst $end
$var parameter 3 & S0 $end
$var parameter 3 ' S1 $end
$var parameter 3 ( S2 $end
$var parameter 3 ) S3 $end
$var parameter 4 * S4 $end
$var reg 2 + done_moore [1:0] $end
$var reg 3 , nextstate [2:0] $end
$var reg 3 - presentstate [2:0] $end
$upscope $end
$upscope $end
$enddefinitions $end
$comment Show the parameter values. $end
$dumpall
b100 *
b11 )
b10 (
b1 '
b0 &
$end
#0
$dumpvars
b0 -
b1 ,
b0 +
b0 %
1$
b0 #
0"
b0 !
$end
#5
1"
#10
0"
0$
#15
b1 -
1"
#20
0"
#25
1"
#30
b10 ,
0"
b110 #
b110 %
#35
b0 ,
b10 -
1"
#40
b11 ,
0"
b0 #
b0 %
#45
b1 ,
b11 -
1"
#50
b100 ,
0"
b110 #
b110 %
#55
b11 !
b11 +
b100 -
1"
#60
b11 ,
0"
b0 #
b0 %
#65
b1 ,
b0 !
b0 +
b11 -
1"
#70
b100 ,
0"
b110 #
b110 %
#75
b11 !
b11 +
b100 -
1"
#80
b11 ,
0"
b0 #
b0 %
#85
b1 ,
b0 !
b0 +
b11 -
1"
#90
b0 ,
0"
b111 #
b111 %
#95
b0 -
1"
#100
b1 ,
0"
b0 #
b0 %
#105
b1 -
1"
#110
b10 ,
0"
b110 #
b110 %
#115
b0 ,
b10 -
1"
#120
b11 ,
0"
b0 #
b0 %
#125
b1 ,
b11 -
1"
#130
b0 ,
0"
b1 #
b1 %
#135
b0 -
1"
#140
b1 ,
0"
b0 #
b0 %
#145
b1 -
1"
#150
b10 ,
0"
b110 #
b110 %
#155
b0 ,
b10 -
1"
#160
b11 ,
0"
b0 #
b0 %
#165
b1 ,
b11 -
1"
#170
b0 ,
0"
b10 #
b10 %
#175
b0 -
1"
