OnClass/led.v
module counter (
  input clk, rst,
  output reg [6:0] seg1, seg2
);
reg [3:0] out1, out2;

always @(posedge clk or posedge rst) begin
  if (rst) begin
    out1 <= 4'b0000;
    out2 <= 4'b0001; //bắt đầu từ 1
  end
  else begin  
    if (out2 == 4'b1001) begin
        out2 <= 4'b0000;
        out1 <= out1 + 4'b0001;
    end
    else begin
        out2 <= out2 + 4'b0001;
    end

   if (out1 == 4'b1001 && out2 == 4'b1001) begin
     out1 <= 4'b0000;
     out2 <= 4'b0001;
   end
  end 
end 
function [6:0] decode_7seg;
    input [3:0] num;
    case (num)
      4'b0000: decode_7seg = 7'b0111111; // 0
      4'b0001: decode_7seg = 7'b0000110; // 1
      4'b0010: decode_7seg = 7'b1011011; // 2
      4'b0011: decode_7seg = 7'b1001111; // 3
      4'b0100: decode_7seg = 7'b1100110; // 4
      4'b0101: decode_7seg = 7'b1101101; // 5
      4'b0110: decode_7seg = 7'b1111101; // 6
      4'b0111: decode_7seg = 7'b0000111; // 7
      4'b1000: decode_7seg = 7'b1111111; // 8
      4'b1001: decode_7seg = 7'b1101111; // 9
      default: decode_7seg = 7'b0000000;
    endcase
  endfunction

always @(*) begin
  seg1 = decode_7seg(out1);
  seg2 = decode_7seg(out2);
    
end
 endmodule

OnClass/tb.v
`timescale 1ps/1ps

module counter_7seg_tb;
  reg clk, rst;
  wire [6:0] seg1, seg2;
  
  counter uut (
    .clk(clk), 
    .rst(rst),  
    .seg1(seg1), 
    .seg2(seg2)
  );
  
   always #5 clk = ~clk;  
  initial begin
    $dumpfile("tb.vcd");
    $dumpvars(0, counter_7seg_tb);
    clk = 0;
    rst = 1;
    #10 rst = 0;
    #1000;
  $finish;
  end
endmodule

OnClass/tb.vcd
$date
	Wed Apr  2 15:37:52 2025
$end
$version
	Icarus Verilog
$end
$timescale
	1ps
$end
$scope module counter_7seg_tb $end
$var wire 7 ! seg2 [6:0] $end
$var wire 7 " seg1 [6:0] $end
$var reg 1 # clk $end
$var reg 1 $ rst $end
$scope module uut $end
$var wire 1 # clk $end
$var wire 1 $ rst $end
$var reg 4 % out1 [3:0] $end
$var reg 4 & out2 [3:0] $end
$var reg 7 ' seg1 [6:0] $end
$var reg 7 ( seg2 [6:0] $end
$scope function decode_7seg $end
$var reg 4 ) num [3:0] $end
$upscope $end
$upscope $end
$upscope $end
$enddefinitions $end
$comment Show the parameter values. $end
$dumpall
$end
#0
$dumpvars
b1 )
b110 (
b111111 '
b1 &
b0 %
1$
0#
b111111 "
b110 !
$end
#5
1#
#10
0#
0$
#15
b1011011 !
b1011011 (
b10 )
b10 &
1#
#20
0#
#25
b1001111 !
b1001111 (
b11 )
b11 &
1#
#30
0#
#35
b1100110 !
b1100110 (
b100 )
b100 &
1#
#40
0#
#45
b1101101 !
b1101101 (
b101 )
b101 &
1#
#50
0#
#55
b1111101 !
b1111101 (
b110 )
b110 &
1#
#60
0#
#65
b111 !
b111 (
b111 )
b111 &
1#
#70
0#
#75
b1111111 !
b1111111 (
b1000 )
b1000 &
1#
#80
0#
#85
b1101111 !
b1101111 (
b1001 )
b1001 &
1#
#90
0#
#95
b111111 !
b111111 (
b110 "
b110 '
b0 )
b1 %
b0 &
1#
#100
0#
#105
b110 !
b110 (
b1 )
b1 &
1#
#110
0#
#115
b1011011 !
b1011011 (
b10 )
b10 &
1#
#120
0#
#125
b1001111 !
b1001111 (
b11 )
b11 &
1#
#130
0#
#135
b1100110 !
b1100110 (
b100 )
b100 &
1#
#140
0#
#145
b1101101 !
b1101101 (
b101 )
b101 &
1#
#150
0#
#155
b1111101 !
b1111101 (
b110 )
b110 &
1#
#160
0#
#165
b111 !
b111 (
b111 )
b111 &
1#
#170
0#
#175
b1111111 !
b1111111 (
b1000 )
b1000 &
1#
#180
0#
#185
b1101111 !
b1101111 (
b1001 )
b1001 &
1#
#190
0#
#195
b111111 !
b111111 (
b1011011 "
b1011011 '
b0 )
b10 %
b0 &
1#
#200
0#
#205
b110 !
b110 (
b1 )
b1 &
1#
#210
0#
#215
b1011011 !
b1011011 (
b10 )
b10 &
1#
#220
0#
#225
b1001111 !
b1001111 (
b11 )
b11 &
1#
#230
0#
#235
b1100110 !
b1100110 (
b100 )
b100 &
1#
#240
0#
#245
b1101101 !
b1101101 (
b101 )
b101 &
1#
#250
0#
#255
b1111101 !
b1111101 (
b110 )
b110 &
1#
#260
0#
#265
b111 !
b111 (
b111 )
b111 &
1#
#270
0#
#275
b1111111 !
b1111111 (
b1000 )
b1000 &
1#
#280
0#
#285
b1101111 !
b1101111 (
b1001 )
b1001 &
1#
#290
0#
#295
b111111 !
b111111 (
b1001111 "
b1001111 '
b0 )
b11 %
b0 &
1#
#300
0#
#305
b110 !
b110 (
b1 )
b1 &
1#
#310
0#
#315
b1011011 !
b1011011 (
b10 )
b10 &
1#
#320
0#
#325
b1001111 !
b1001111 (
b11 )
b11 &
1#
#330
0#
#335
b1100110 !
b1100110 (
b100 )
b100 &
1#
#340
0#
#345
b1101101 !
b1101101 (
b101 )
b101 &
1#
#350
0#
#355
b1111101 !
b1111101 (
b110 )
b110 &
1#
#360
0#
#365
b111 !
b111 (
b111 )
b111 &
1#
#370
0#
#375
b1111111 !
b1111111 (
b1000 )
b1000 &
1#
#380
0#
#385
b1101111 !
b1101111 (
b1001 )
b1001 &
1#
#390
0#
#395
b111111 !
b111111 (
b1100110 "
b1100110 '
b0 )
b100 %
b0 &
1#
#400
0#
#405
b110 !
b110 (
b1 )
b1 &
1#
#410
0#
#415
b1011011 !
b1011011 (
b10 )
b10 &
1#
#420
0#
#425
b1001111 !
b1001111 (
b11 )
b11 &
1#
#430
0#
#435
b1100110 !
b1100110 (
b100 )
b100 &
1#
#440
0#
#445
b1101101 !
b1101101 (
b101 )
b101 &
1#
#450
0#
#455
b1111101 !
b1111101 (
b110 )
b110 &
1#
#460
0#
#465
b111 !
b111 (
b111 )
b111 &
1#
#470
0#
#475
b1111111 !
b1111111 (
b1000 )
b1000 &
1#
#480
0#
#485
b1101111 !
b1101111 (
b1001 )
b1001 &
1#
#490
0#
#495
b111111 !
b111111 (
b1101101 "
b1101101 '
b0 )
b101 %
b0 &
1#
#500
0#
#505
b110 !
b110 (
b1 )
b1 &
1#
#510
0#
#515
b1011011 !
b1011011 (
b10 )
b10 &
1#
#520
0#
#525
b1001111 !
b1001111 (
b11 )
b11 &
1#
#530
0#
#535
b1100110 !
b1100110 (
b100 )
b100 &
1#
#540
0#
#545
b1101101 !
b1101101 (
b101 )
b101 &
1#
#550
0#
#555
b1111101 !
b1111101 (
b110 )
b110 &
1#
#560
0#
#565
b111 !
b111 (
b111 )
b111 &
1#
#570
0#
#575
b1111111 !
b1111111 (
b1000 )
b1000 &
1#
#580
0#
#585
b1101111 !
b1101111 (
b1001 )
b1001 &
1#
#590
0#
#595
b111111 !
b111111 (
b1111101 "
b1111101 '
b0 )
b110 %
b0 &
1#
#600
0#
#605
b110 !
b110 (
b1 )
b1 &
1#
#610
0#
#615
b1011011 !
b1011011 (
b10 )
b10 &
1#
#620
0#
#625
b1001111 !
b1001111 (
b11 )
b11 &
1#
#630
0#
#635
b1100110 !
b1100110 (
b100 )
b100 &
1#
#640
0#
#645
b1101101 !
b1101101 (
b101 )
b101 &
1#
#650
0#
#655
b1111101 !
b1111101 (
b110 )
b110 &
1#
#660
0#
#665
b111 !
b111 (
b111 )
b111 &
1#
#670
0#
#675
b1111111 !
b1111111 (
b1000 )
b1000 &
1#
#680
0#
#685
b1101111 !
b1101111 (
b1001 )
b1001 &
1#
#690
0#
#695
b111111 !
b111111 (
b111 "
b111 '
b0 )
b111 %
b0 &
1#
#700
0#
#705
b110 !
b110 (
b1 )
b1 &
1#
#710
0#
#715
b1011011 !
b1011011 (
b10 )
b10 &
1#
#720
0#
#725
b1001111 !
b1001111 (
b11 )
b11 &
1#
#730
0#
#735
b1100110 !
b1100110 (
b100 )
b100 &
1#
#740
0#
#745
b1101101 !
b1101101 (
b101 )
b101 &
1#
#750
0#
#755
b1111101 !
b1111101 (
b110 )
b110 &
1#
#760
0#
#765
b111 !
b111 (
b111 )
b111 &
1#
#770
0#
#775
b1111111 !
b1111111 (
b1000 )
b1000 &
1#
#780
0#
#785
b1101111 !
b1101111 (
b1001 )
b1001 &
1#
#790
0#
#795
b111111 !
b111111 (
b1111111 "
b1111111 '
b0 )
b1000 %
b0 &
1#
#800
0#
#805
b110 !
b110 (
b1 )
b1 &
1#
#810
0#
#815
b1011011 !
b1011011 (
b10 )
b10 &
1#
#820
0#
#825
b1001111 !
b1001111 (
b11 )
b11 &
1#
#830
0#
#835
b1100110 !
b1100110 (
b100 )
b100 &
1#
#840
0#
#845
b1101101 !
b1101101 (
b101 )
b101 &
1#
#850
0#
#855
b1111101 !
b1111101 (
b110 )
b110 &
1#
#860
0#
#865
b111 !
b111 (
b111 )
b111 &
1#
#870
0#
#875
b1111111 !
b1111111 (
b1000 )
b1000 &
1#
#880
0#
#885
b1101111 !
b1101111 (
b1001 )
b1001 &
1#
#890
0#
#895
b111111 !
b111111 (
b0 )
b1101111 "
b1101111 '
b1001 %
b0 &
1#
#900
0#
#905
b110 !
b110 (
b1 )
b1 &
1#
#910
0#
#915
b1011011 !
b1011011 (
b10 )
b10 &
1#
#920
0#
#925
b1001111 !
b1001111 (
b11 )
b11 &
1#
#930
0#
#935
b1100110 !
b1100110 (
b100 )
b100 &
1#
#940
0#
#945
b1101101 !
b1101101 (
b101 )
b101 &
1#
#950
0#
#955
b1111101 !
b1111101 (
b110 )
b110 &
1#
#960
0#
#965
b111 !
b111 (
b111 )
b111 &
1#
#970
0#
#975
b1111111 !
b1111111 (
b1000 )
b1000 &
1#
#980
0#
#985
b1101111 !
b1101111 (
b1001 )
b1001 &
1#
#990
0#
#995
b110 !
b110 (
b111111 "
b111111 '
b1 )
b0 %
b1 &
1#
#1000
0#
#1005
b1011011 !
b1011011 (
b10 )
b10 &
1#
